scrnaseq/__init__.py
scrnaseq/fetch_dataset.py
scrnaseq/list_datasets.py
scrnaseq/list_versions.py
scrnaseq/polish_dataset.py
scrnaseq/save_dataset.py
scrnaseq/search_datasets.py
scrnaseq/upload_dataset.py
scrnaseq/utils.py
scrnaseq-0.3.1.dist-info/LICENSE.txt
scrnaseq-0.3.1.dist-info/METADATA
scrnaseq-0.3.1.dist-info/WHEEL
scrnaseq-0.3.1.dist-info/top_level.txt
scrnaseq-0.3.1.dist-info/RECORD
