Metadata-Version: 2.1
Name: scrnaseq
Version: 0.3.1
Summary: Collection of Public Single-Cell RNA-Seq Datasets
Home-page: https://github.com/biocpy/scrnaseq
Author: Jayaram Kancherla
Author-email: jayaram.kancherla@gmail.com
License: MIT
Project-URL: Documentation, https://github.com/biocpy/scrnaseq
Platform: any
Classifier: Development Status :: 4 - Beta
Classifier: Programming Language :: Python
Requires-Python: >=3.9
License-File: LICENSE.txt
Requires-Dist: importlib-metadata; python_version < "3.8"
Requires-Dist: dolomite_base>=0.4.2
Requires-Dist: dolomite_matrix
Requires-Dist: dolomite_sce
Requires-Dist: gypsum_client>=0.1.3
Requires-Dist: delayedarray>=0.5.1
Requires-Dist: summarizedexperiment
Requires-Dist: singlecellexperiment
Provides-Extra: optional
Requires-Dist: anndata; extra == "optional"
Requires-Dist: scipy; extra == "optional"
Provides-Extra: testing
Requires-Dist: setuptools; extra == "testing"
Requires-Dist: pytest; extra == "testing"
Requires-Dist: pytest-cov; extra == "testing"
Requires-Dist: scipy; extra == "testing"
Requires-Dist: anndata; extra == "testing"
